Metadata-Version: 2.1
Name: objw
Version: 5
Summary: objects workdir
Author-email: Bart Thate <rssbotd@gmail.com>
License: Public Domain
Project-URL: home, https://pypi.org/project/objw
Project-URL: bugs, https://github.com/rssbotd/objw/issues
Project-URL: source, https://github.com/rssbotd/objw
Classifier: Development Status :: 3 - Alpha
Classifier: License :: Public Domain
Classifier: Operating System :: Unix
Classifier: Programming Language :: Python
Classifier: Topic :: Utilities
